{"ongoing_trials": {}, "hyperparameters": {"space": [{"class_name": "Int", "config": {"name": "input_units", "default": null, "min_value": 32, "max_value": 256, "step": 32, "sampling": null}}, {"class_name": "Int", "config": {"name": "n_layers", "default": null, "min_value": 1, "max_value": 4, "step": 1, "sampling": null}}, {"class_name": "Int", "config": {"name": "conv_0_units", "default": null, "min_value": 32, "max_value": 256, "step": 32, "sampling": null}}], "values": {"input_units": 32, "n_layers": 1, "conv_0_units": 32}}, "seed": 6439, "seed_state": 6442, "tried_so_far": ["a219ba0d28a70c349cfaf52f4c0a007e"]}